MANIFEST.in
README.md
setup.cfg
setup.py
src/cmaqml/__init__.py
src/cmaqml/__main__.py
src/cmaqml/driver.py
src/cmaqml/opts.py
src/cmaqml.egg-info/PKG-INFO
src/cmaqml.egg-info/SOURCES.txt
src/cmaqml.egg-info/dependency_links.txt
src/cmaqml.egg-info/not-zip-safe
src/cmaqml.egg-info/top_level.txt
src/cmaqml/models/__init__.py
src/cmaqml/models/voronoi.py
src/cmaqml/obs/__init__.py
src/cmaqml/obs/aqs.py
src/cmaqml/testcase/__init__.py
src/cmaqml/testcase/input/GRIDCRO2D.108US2.35L.160101.nc
src/cmaqml/testcase/input/GRIDDESC
src/cmaqml/testcase/input/O3_8HRMAX.LST.Y_24.2016fh.v531.108US2.5-9.nc
src/cmaqml/testcase/input/config.json
src/cmaqml/testcase/input/daily_44201_20160715.zip
src/cmaqml/testcase/input/daily_88101_20160115.zip
src/cmaqml/testcase/input/dailyavg.LST.Y_24.2016fh.v531.108US2.01.nc
src/cmaqml/testcase/input/gpw_v4_une_atotpopbt_densy_108US2.IOAPI.nc
src/cmaqml/testcase/input/make_test.py
src/cmaqml/testcase/input/.ipynb_checkpoints/GRIDDESC-checkpoint