Metadata-Version: 2.1
Name: cmaqml
Version: 0.2.1
Summary: A simple package for applying Machine Learnign to CMAQ and associated obs.
Home-page: https://github.com/barronh/cmaqml
Author: Barron Henderson
Author-email: barronh@gmail.com
License: UNKNOWN
Project-URL: Bug Tracker, https://github.com/barronh/cmaqml/issues
Platform: UNKNOWN
Classifier: Programming Language :: Python :: 3
Classifier: License :: CC0 1.0 Universal (CC0 1.0) Public Domain Dedication
Classifier: Operating System :: OS Independent
Requires-Python: >=3.6
